CHANGES.txt
MANIFEST.in
README.txt
setup.py
docs/INSTALL.txt
docs/INTRO.txt
docs/LICENSE.GPL
docs/LICENSE.txt
docs/NEWS.txt
docs/TODO.txt
docs/tutorial_part2.rst
kss/__init__.py
kss.core.egg-info/PKG-INFO
kss.core.egg-info/SOURCES.txt
kss.core.egg-info/dependency_links.txt
kss.core.egg-info/namespace_packages.txt
kss.core.egg-info/not-zip-safe
kss.core.egg-info/requires.txt
kss.core.egg-info/top_level.txt
kss/core/BeautifulSoup.py
kss/core/EXTERNALS.TXT
kss/core/INSTALL.txt
kss/core/__init__.py
kss/core/actionwrapper.py
kss/core/browserview.py
kss/core/commands.py
kss/core/concatresource.zcml
kss/core/config.py
kss/core/configure.zcml
kss/core/deprecated.py
kss/core/interfaces.py
kss/core/kss.core-configure.zcml
kss/core/kss.core-meta.zcml
kss/core/kssview.py
kss/core/kssview.txt
kss/core/meta.zcml
kss/core/parsers.py
kss/core/permission.zcml
kss/core/selectors.py
kss/core/siteview.txt
kss/core/svnignore
kss/core/ttwapi.py
kss/core/unicode_quirks.py
kss/core/browser/errorresponse.pt
kss/core/browser/kss_javascript.pt
kss/core/browser/kukitresponse.pt
kss/core/dtds/xhtml-lat1.ent
kss/core/dtds/xhtml-special.ent
kss/core/dtds/xhtml-symbol.ent
kss/core/dtds/xhtml1-transitional.dtd
kss/core/kukit/CHANGES.txt
kss/core/kukit/tests.bat
kss/core/kukit/version.txt
kss/core/kukit/3rd_party/LICENSE.txt
kss/core/kukit/3rd_party/MochiKit.js
kss/core/kukit/3rd_party/base2-dom-fp-20070816.js
kss/core/kukit/3rd_party/base2-dom-fp-20080312.js
kss/core/kukit/3rd_party/base2-dom-fp.js
kss/core/kukit/3rd_party/cssQuery-compat.js
kss/core/kukit/3rd_party/cssQuery.js
kss/core/kukit/3rd_party/sarissa.js
kss/core/kukit/3rd_party/firebuglite/errorIcon.png
kss/core/kukit/3rd_party/firebuglite/firebug.css
kss/core/kukit/3rd_party/firebuglite/firebug.html
kss/core/kukit/3rd_party/firebuglite/firebug.js
kss/core/kukit/3rd_party/firebuglite/firebugx.js
kss/core/kukit/3rd_party/firebuglite/infoIcon.png
kss/core/kukit/3rd_party/firebuglite/warningIcon.png
kss/core/kukit/3rd_party/johnnydebris.net/dommer/CHANGES.txt
kss/core/kukit/3rd_party/johnnydebris.net/dommer/LICENSE.txt
kss/core/kukit/3rd_party/johnnydebris.net/dommer/README.txt
kss/core/kukit/3rd_party/johnnydebris.net/dommer/conftest.py
