Metadata-Version: 1.0
Name: kss.core
Version: 1.6.4
Summary: KSS (Kinetic Style Sheets) core framework
Home-page: http://kssproject.org
Author: KSS Project
Author-email: kss-devel@codespeak.net
License: GPL
Platform: UNKNOWN
Classifier: Framework :: Zope2
Classifier: Framework :: Zope3
Classifier: Programming Language :: Python
Classifier: Topic :: Software Development :: Libraries :: Python Modules
